pdfFileCheck/__init__.py
pdfFileCheck/check.py
pdfFileCheck-1.0.dist-info/LICENSE.txt
pdfFileCheck-1.0.dist-info/METADATA
pdfFileCheck-1.0.dist-info/WHEEL
pdfFileCheck-1.0.dist-info/entry_points.txt
pdfFileCheck-1.0.dist-info/top_level.txt
pdfFileCheck-1.0.dist-info/RECORD
